{
  "generatedAt": "2026-07-09T20:53:07.841Z",
  "cityKey": "oslo",
  "cityName": "Oslo",
  "municipalities": [
    "Oslo",
    "Bærum",
    "Asker",
    "Lillestrøm",
    "Lørenskog",
    "Nordre Follo",
    "Rælingen",
    "Nittedal",
    "Lier"
  ],
  "limit": 5,
  "source": "Badetemperaturer levert av Yr",
  "updatedAt": "2026-07-09T22:00:00+02:00",
  "items": [
    {
      "navn": "Østernvann",
      "omrade": "Bærum",
      "temperatur": 22,
      "maltKlokken": "20:30",
      "locationId": "1-72640",
      "latitude": 59.96872,
      "longitude": 10.58186,
      "time": "2026-07-09T20:30:00+02:00"
    },
    {
      "navn": "Tussetjernet",
      "omrade": "Nordre Follo",
      "temperatur": 21.8,
      "maltKlokken": "18:24",
      "locationId": "1-74568",
      "latitude": 59.76284,
      "longitude": 10.8289,
      "time": "2026-07-05T18:24:41+02:00"
    },
    {
      "navn": "Storøyodden",
      "omrade": "Bærum",
      "temperatur": 21.6,
      "maltKlokken": "16:00",
      "locationId": "0-10014",
      "latitude": 59.88819,
      "longitude": 10.59302,
      "time": "2026-07-09T16:00:52+02:00"
    },
    {
      "navn": "Huk naturiststrand",
      "omrade": "Oslo",
      "temperatur": 21.5,
      "maltKlokken": "16:45",
      "locationId": "0-10055",
      "latitude": 59.89647,
      "longitude": 10.67231,
      "time": "2026-07-09T16:45:00+02:00"
    },
    {
      "navn": "Hvalstrand",
      "omrade": "Asker",
      "temperatur": 21.1,
      "maltKlokken": "16:00",
      "locationId": "2-3151302",
      "latitude": 59.84215,
      "longitude": 10.48857,
      "time": "2026-07-09T16:00:49+02:00"
    }
  ]
}
